{
  "version": "6",
  "dialect": "sqlite",
  "id": "cad55417-20dd-4975-b62c-0506d7fd8da1",
  "prevId": "88b27700-2d4c-413f-af19-973c42f54bff",
  "tables": {
    "session": {
      "name": "session",
      "columns": {
        "id": {
          "name": "id",
          "type": "text",
          "primaryKey": true,
          "notNull": true,
          "autoincrement": false
        },
        "user_id": {
          "name": "user_id",
          "type": "text",
          "primaryKey": false,
          "notNull": true,
          "autoincrement": false
        },
        "expires_at": {
          "name": "expires_at",
          "type": "integer",
          "primaryKey": false,
          "notNull": true,
          "autoincrement": false
        }
      },
      "indexes": {},
      "foreignKeys": {
        "session_user_id_user_id_fk": {
          "name": "session_user_id_user_id_fk",
          "tableFrom": "session",
          "tableTo": "user",
          "columnsFrom": [
            "user_id"
          ],
          "columnsTo": [
            "id"
          ],
          "onDelete": "no action",
          "onUpdate": "no action"
        }
      },
      "compositePrimaryKeys": {},
      "uniqueConstraints": {}
    },
    "user": {
      "name": "user",
      "columns": {
        "id": {
          "name": "id",
          "type": "text",
          "primaryKey": true,
          "notNull": true,
          "autoincrement": false
        },
        "name": {
          "name": "name",
          "type": "text",
          "primaryKey": false,
          "notNull": true,
          "autoincrement": false
        },
        "email": {
          "name": "email",
          "type": "text",
          "primaryKey": false,
          "notNull": true,
          "autoincrement": false
        },
        "access_at": {
          "name": "access_at",
          "type": "text",
          "primaryKey": false,
          "notNull": false,
          "autoincrement": false,
          "default": "CURRENT_TIMESTAMP"
        },
        "created_at": {
          "name": "created_at",
          "type": "text",
          "primaryKey": false,
          "notNull": false,
          "autoincrement": false,
          "default": "CURRENT_TIMESTAMP"
        }
      },
      "indexes": {
        "user_email_unique": {
          "name": "user_email_unique",
          "columns": [
            "email"
          ],
          "isUnique": true
        },
        "uid": {
          "name": "uid",
          "columns": [
            "name"
          ],
          "isUnique": true
        }
      },
      "foreignKeys": {},
      "compositePrimaryKeys": {},
      "uniqueConstraints": {}
    }
  },
  "enums": {},
  "_meta": {
    "schemas": {},
    "tables": {
      "\"users_sessions\"": "\"session\"",
      "\"users\"": "\"user\""
    },
    "columns": {}
  }
}